arithmat/__init__.py
arithmat/arithmetic_matroid.py
arithmat/shnf.py
arithmat/test.sage.py
arithmat-1.1.2.dist-info/LICENSE.md
arithmat-1.1.2.dist-info/METADATA
arithmat-1.1.2.dist-info/WHEEL
arithmat-1.1.2.dist-info/top_level.txt
arithmat-1.1.2.dist-info/RECORD
