Metadata-Version: 2.1
Name: arithmat
Version: 1.1.2
Summary: Sage implementation of arithmetic matroids and toric arrangements
Home-page: https://github.com/giove91/arithmat
Author: Roberto Pagaria, Giovanni Paolini
Author-email: giovanni.paolini@sns.it
License: GPLv3
Project-URL: Source, https://github.com/giove91/arithmat
Project-URL: Tracker, https://github.com/giove91/arithmat/issues
Keywords: SageMath packaging
Platform: UNKNOWN
Classifier: Development Status :: 3 - Alpha
Classifier: Intended Audience :: Science/Research
Classifier: Topic :: Software Development :: Build Tools
Classifier: Topic :: Scientific/Engineering :: Mathematics
Classifier: License :: OSI Approved :: GNU General Public License v3 (GPLv3)
Classifier: Programming Language :: Python
Requires-Python: >=2.7
Requires-Dist: sage-package
Requires-Dist: networkx (~=2.2)
